geysergen/__init__.py
geysergen/generator.py
geysergen/docs/README.md
geysergen/docs/README.pdf
geysergen/docs/schema_doc.pdf
geysergen/formatter/LICENSE.txt
geysergen/formatter/verible-verilog-format
geysergen/formatter/verible-verilog-format.exe
geysergen/generic_modules/__init__.py
geysergen/generic_modules/intel/__init__.py
geysergen/generic_modules/intel/avalon_byte_to_word.py
geysergen/generic_modules/intel/avalon_pipline.py
geysergen/generic_modules/intel/avalon_pipline_hbm.py
geysergen/generic_modules/intel/dual_port_sram.py
geysergen/generic_modules/intel/mm_interconnect.py
geysergen/generic_modules/intel/mm_interconnect_generate.py
geysergen/generic_modules/intel/sync_done.py
geysergen/generic_modules/intel/special_mod_json/avalon_byte_to_word.vgen.json
geysergen/generic_modules/intel/special_mod_json/avalon_pipeline.vgen.json
geysergen/generic_modules/intel/special_mod_json/done_sync.vgen.json
geysergen/generic_modules/intel/special_mod_json/dual_port_sram.vgen.json
geysergen/generic_modules/intel/special_mod_json/full_pipeline.vgen.json
geysergen/generic_modules/intel/special_mod_json/single_port_sram.vgen.json
geysergen/generic_modules/intel/verilog/HBM_interface_pipeline.v
geysergen/generic_modules/intel/verilog/avalon_byte_to_word.v
geysergen/generic_modules/intel/verilog/avalon_demux1xN.v
geysergen/generic_modules/intel/verilog/avalon_muxNx1.v
geysergen/generic_modules/intel/verilog/dual_port_sram.v
geysergen/generic_modules/intel/verilog/fullpipeline.v
geysergen/generic_modules/intel/verilog/interface_pipeline.v
geysergen/generic_modules/intel/verilog/single_port_sram.v
geysergen/generic_modules/intel/verilog/sync_done.v
geysergen/generic_modules/taxi/LICENSE_WARNING
geysergen/generic_modules/xilinx/__init__.py
geysergen/generic_modules/xilinx/series7/__init__.py
geysergen/generic_modules/xilinx/series7/bram_interconnect.py
geysergen/generic_modules/xilinx/series7/true_dual_port_sram.py
geysergen-0.0.2.dist-info/METADATA
geysergen-0.0.2.dist-info/WHEEL
geysergen-0.0.2.dist-info/entry_points.txt
geysergen-0.0.2.dist-info/licenses/LICENSE
geysergen-0.0.2.dist-info/RECORD
