Metadata-Version: 2.4
Name: geysergen
Version: 0.0.2
Summary: A Python framework for hardware design integration
Project-URL: Homepage, https://github.com/SLAM-Lab/GEYSER
Project-URL: Codebase, https://github.com/SLAM-Lab/GEYSER
Project-URL: Issues, https://github.com/SLAM-Lab/GEYSER/issues
Author-email: Austin James <ajamesut@utexas.edu>
License-File: LICENSE
Classifier: Development Status :: 4 - Beta
Classifier: License :: OSI Approved :: MIT License
Classifier: Operating System :: OS Independent
Classifier: Programming Language :: Python :: 3
Requires-Python: >=3.8
Requires-Dist: jsonschema
Requires-Dist: lxml
